dbschema/__init__.py
dbschema/__main__.py
dbschema/schema_change.py
dbschema-1.4.3.dist-info/LICENSE
dbschema-1.4.3.dist-info/METADATA
dbschema-1.4.3.dist-info/WHEEL
dbschema-1.4.3.dist-info/entry_points.txt
dbschema-1.4.3.dist-info/top_level.txt
dbschema-1.4.3.dist-info/RECORD
