Metadata-Version: 2.1
Name: dbschema
Version: 1.4.3
Summary: Schema migration made easy
Home-page: https://github.com/gabfl/dbschema
Author: Gabriel Bordeaux
Author-email: pypi@gab.lc
License: MIT
Platform: UNKNOWN
Classifier: Topic :: Database
Classifier: Topic :: Database :: Database Engines/Servers
Classifier: License :: OSI Approved :: MIT License
Classifier: Operating System :: MacOS
Classifier: Operating System :: POSIX :: Linux
Classifier: Natural Language :: English
Classifier: Programming Language :: Python :: 3
Classifier: Programming Language :: Python
Classifier: Development Status :: 4 - Beta
Requires-Dist: argparse
Requires-Dist: PyYAML
Requires-Dist: pymysql
Requires-Dist: psycopg2-binary
